{
  "doc_id": "bostonhousing_faq_031_what_are_major_life_activities",
  "source_url": "https://www.bostonhousing.org/en/FAQ.aspx",
  "source_name": "bostonhousing",
  "title": "[Reasonable Accommodation] What are “major life activities”?",
  "section_headers": [
    "Reasonable Accommodation"
  ],
  "content": "**Q: What are “major life activities”?**\n\nExamples of major life activities include, but are not limited to, the ability to walk, see, hear, breathe, think, read, or care for oneself.",
  "content_type": "faq",
  "crawl_depth": 0,
  "scraped_at": "2026-03-17T23:01:23.369791+00:00",
  "legal_citations": [],
  "parent_url": null,
  "content_hash": "f9593bae3012497990845f677eff84aed7c7d1ad4b20a3f8cf87120a23c2566d"
}