{
  "doc_id": "bostonhousing_faq_046_i_was_determined_not_eligible_for_housing_assistance_can_i_a",
  "source_url": "https://www.bostonhousing.org/en/FAQ.aspx",
  "source_name": "bostonhousing",
  "title": "[Receiving an Offer or Rejection] I was determined not eligible for housing assistance. Can I appeal?",
  "section_headers": [
    "Receiving an Offer or Rejection"
  ],
  "content": "**Q: I was determined not eligible for housing assistance. Can I appeal?**\n\nIf an applicant is determined not eligible for housing, the applicant has the right to file an appeal with the BHA. For more information on filing an appeal, applicants may call the BHA Office ofGrievances and Appeals.",
  "content_type": "faq",
  "crawl_depth": 0,
  "scraped_at": "2026-03-17T23:01:23.373957+00:00",
  "legal_citations": [],
  "parent_url": null,
  "content_hash": "ac3c47e368f14c89dcf97e23d4d0c79cbfd20caf33c3ef1589e065d45152da47"
}